LICENSE.md
MANIFEST.in
README.rst
setup.py
nest/__init__.py
nest/command_line.py
nest/helpers.py
nest/nest.py
nest/utils.py
python_nest.egg-info/PKG-INFO
python_nest.egg-info/SOURCES.txt
python_nest.egg-info/dependency_links.txt
python_nest.egg-info/entry_points.txt
python_nest.egg-info/requires.txt
python_nest.egg-info/top_level.txt