Metadata-Version: 1.0
Name: python-nest
Version: 4.0.4
Summary: Python API and command line tool for talking to the Nest™ Thermostat
Home-page: https://github.com/jkoelker/python-nest/
Author: Jason Kölker
Author-email: jason@koelker.net
License: UNKNOWN
Keywords: nest thermostat
Platform: UNKNOWN
